{
    "line1": [
        {
            "avatar": "/img/test-avatar.webp",
            "text": "柯总最帅柯总最帅柯总最帅柯总最帅"
        },
        {
            "avatar": "/img/test-avatar.webp",
            "text": "柯总最帅"
        },
        {
            "avatar": "/img/test-avatar.webp",
            "text": "柯总最帅柯总最帅柯总最帅柯总最帅"
        },
        {
            "avatar": "/img/test-avatar.webp",
            "text": "柯总最帅"
        }
    ],
    "line2": [
        {
            "avatar": "/img/test-avatar.webp",
            "text": "柯总最帅柯总最帅柯总最帅柯总最帅"
        },
        {
            "avatar": "/img/test-avatar.webp",
            "text": "柯总最帅"
        },
        {
            "avatar": "/img/test-avatar.webp",
            "text": "柯总最帅柯总最帅柯总最帅柯总最帅"
        },
        {
            "avatar": "/img/test-avatar.webp",
            "text": "柯总最帅"
        },
        {
            "avatar": "/img/test-avatar.webp",
            "text": "柯总最帅"
        }
    ]
}